{
  "parent": "minecraft:recipes/root",
  "criteria": {
    "has_crystal_normal": {
      "conditions": {
        "items": [
          {
            "items": [
              "my_mod:crystal_normal"
            ]
          }
        ]
      },
      "trigger": "minecraft:inventory_changed"
    },
    "has_the_recipe": {
      "conditions": {
        "recipe": "my_mod:node_standard"
      },
      "trigger": "minecraft:recipe_unlocked"
    }
  },
  "requirements": [
    [
      "has_crystal_normal",
      "has_the_recipe"
    ]
  ],
  "rewards": {
    "recipes": [
      "my_mod:node_standard"
    ]
  },
  "sends_telemetry_event": false
}